cbrapi/__init__.py
cbrapi/cbr_settings.py
cbrapi/currency.py
cbrapi/helpers.py
cbrapi/metals.py
cbrapi/rates.py
cbrapi/reserves.py
cbrapi/ruonia.py
cbrapi-0.1.3.dist-info/METADATA
cbrapi-0.1.3.dist-info/WHEEL
cbrapi-0.1.3.dist-info/RECORD
