Metadata-Version: 2.3
Name: cbrapi
Version: 0.1.3
Summary: Python interface for Central Bank of Russia (CBR) API
Author: AAARRRT
Author-email: artiomsalazov@gmail.com
Requires-Python: >=3.10,<4.0.0
Classifier: Programming Language :: Python :: 3
Classifier: Programming Language :: Python :: 3.10
Classifier: Programming Language :: Python :: 3.11
Classifier: Programming Language :: Python :: 3.12
Classifier: Programming Language :: Python :: 3.13
Requires-Dist: lxml
Requires-Dist: pandas (>=2.3.2,<3.0.0)
Requires-Dist: requests
Requires-Dist: suds-py3
